{"cameraMode":{"drawMode":0,"name":"Shaded","section":"Shading Mode"},"sceneLighting":true,"audioPlay":false,"sceneViewState":{"m_AlwaysRefresh":false,"showFog":true,"showSkybox":true,"showFlares":true,"showImageEffects":true,"showParticleSystems":true,"showVisualEffectGraphs":true,"m_FxEnabled":true},"in2DMode":false,"pivot":{"x":-5.34539270401001,"y":-1.982153296470642,"z":2.0001375675201418},"rotation":{"x":-0.1486452966928482,"y":0.320574551820755,"z":-0.051013823598623279,"w":-0.9340961575508118},"size":10.281904220581055,"orthographic":false}